[
  {
    "createdAt": "2026-01-19T11:44:51.101Z",
    "championName": "Azir",
    "username": "azm0deus1467",
    "user_sub": "a4b8a428-e0c1-70a9-3863-3bf9b3acff4f",
    "id": "a5a24b01-7dbc-4a9c-8182-11416ace6ccb",
    "creatorName": "Vô Danh"
  },
  {
    "createdAt": "2025-12-05T11:21:29.759Z",
    "championName": "Azir",
    "username": "lingq",
    "user_sub": "d4882408-b0d1-70bc-e3d3-13ef8cb11069",
    "id": "a5a24b01-7dbc-4a9c-8182-11416ace6ccb",
    "creatorName": "Vô Danh"
  },
  {
    "createdAt": "2026-01-04T06:47:24.714Z",
    "championName": "Yuumi",
    "username": "vuthinh2345",
    "user_sub": "14d8f4d8-a001-7085-e5d5-d2d63f2531ef",
    "id": "b0066f59-784d-4f94-9c89-edd34e27b580",
    "creatorName": "Vô Danh"
  },
  {
    "createdAt": "2025-12-02T03:38:28.972Z",
    "championName": "Vayne",
    "username": "toanproquangau",
    "user_sub": "6498a4b8-a011-70a1-5f28-627c7ea26aa5",
    "id": "1306cc6e-7b71-42f4-8ccb-67daa8cd52db",
    "creatorName": "Vô Danh"
  },
  {
    "createdAt": "2025-11-28T03:30:15.259Z",
    "championName": "Vayne",
    "username": "evin123",
    "user_sub": "64b81448-0021-70b7-759a-080d73ea41fd",
    "id": "1306cc6e-7b71-42f4-8ccb-67daa8cd52db",
    "creatorName": "Vô Danh"
  },
  {
    "createdAt": "2025-11-28T04:29:30.002Z",
    "championName": "Neeko",
    "username": "lingq",
    "user_sub": "d4882408-b0d1-70bc-e3d3-13ef8cb11069",
    "id": "42a36d66-ac0d-4c08-afb8-9d6ee89e7feb",
    "creatorName": "lingq"
  },
  {
    "createdAt": "2026-01-19T11:33:21.187Z",
    "championName": "Elise",
    "username": "azm0deus1467",
    "user_sub": "a4b8a428-e0c1-70a9-3863-3bf9b3acff4f",
    "id": "de918ce7-23a0-4bde-a951-833f0735c75e",
    "creatorName": "Vô Danh"
  },
  {
    "createdAt": "2026-02-27T06:01:55.937Z",
    "championName": "Evelynn",
    "username": "lingq",
    "user_sub": "d4882408-b0d1-70bc-e3d3-13ef8cb11069",
    "id": "1e82eafd-5035-4043-94be-98c8560b6c1e",
    "creatorName": "Vô Danh"
  },
  {
    "createdAt": "2025-12-02T03:38:20.392Z",
    "championName": "Viktor",
    "username": "toanproquangau",
    "user_sub": "6498a4b8-a011-70a1-5f28-627c7ea26aa5",
    "id": "e827e81d-56ee-4d69-8061-f3724f4bfb5a",
    "creatorName": "Vô Danh"
  },
  {
    "createdAt": "2025-12-06T09:40:58.812Z",
    "championName": "Viktor",
    "username": "evin123",
    "user_sub": "64b81448-0021-70b7-759a-080d73ea41fd",
    "id": "e827e81d-56ee-4d69-8061-f3724f4bfb5a",
    "creatorName": "Vô Danh"
  },
  {
    "createdAt": "2025-12-04T13:49:47.376Z",
    "championName": "Viktor",
    "username": "lingq",
    "user_sub": "d4882408-b0d1-70bc-e3d3-13ef8cb11069",
    "id": "e827e81d-56ee-4d69-8061-f3724f4bfb5a",
    "creatorName": "Vô Danh"
  },
  {
    "createdAt": "2025-12-02T03:38:34.101Z",
    "championName": "Pyke",
    "username": "toanproquangau",
    "user_sub": "6498a4b8-a011-70a1-5f28-627c7ea26aa5",
    "id": "948b29d1-6d9f-4e49-82fa-176f4c77fcb8",
    "creatorName": "Vô Danh"
  },
  {
    "createdAt": "2025-11-28T09:32:46.070Z",
    "championName": "Pyke",
    "username": "evin123",
    "user_sub": "64b81448-0021-70b7-759a-080d73ea41fd",
    "id": "948b29d1-6d9f-4e49-82fa-176f4c77fcb8",
    "creatorName": "lingq"
  },
  {
    "createdAt": "2026-01-19T11:32:45.290Z",
    "championName": "Ambessa",
    "username": "azm0deus1467",
    "user_sub": "a4b8a428-e0c1-70a9-3863-3bf9b3acff4f",
    "id": "9181b99a-de78-46a9-82b1-4d71dcced591",
    "creatorName": "Vô Danh"
  },
  {
    "createdAt": "2025-12-05T10:46:03.011Z",
    "championName": "Vua Poro",
    "username": "lingq",
    "user_sub": "d4882408-b0d1-70bc-e3d3-13ef8cb11069",
    "id": "c606620f-9f3d-4482-b243-5bcea986cc60",
    "creatorName": "Vô Danh"
  },
  {
    "createdAt": "2026-01-19T11:32:57.466Z",
    "championName": "Yuumi",
    "username": "azm0deus1467",
    "user_sub": "a4b8a428-e0c1-70a9-3863-3bf9b3acff4f",
    "id": "9b0992f3-3278-49ad-99e8-1d4b326af7d6",
    "creatorName": "Vô Danh"
  },
  {
    "createdAt": "2025-12-02T03:38:24.662Z",
    "championName": "Leblanc",
    "username": "toanproquangau",
    "user_sub": "6498a4b8-a011-70a1-5f28-627c7ea26aa5",
    "id": "dbc794b1-7a1f-43aa-adb1-f6da558c0279",
    "creatorName": "Vô Danh"
  },
  {
    "createdAt": "2025-11-29T08:49:26.674Z",
    "championName": "Leblanc",
    "username": "lingq",
    "user_sub": "d4882408-b0d1-70bc-e3d3-13ef8cb11069",
    "id": "dbc794b1-7a1f-43aa-adb1-f6da558c0279",
    "creatorName": "Vô Danh"
  },
  {
    "createdAt": "2025-11-28T03:30:27.914Z",
    "championName": "Norra",
    "username": "evin123",
    "user_sub": "64b81448-0021-70b7-759a-080d73ea41fd",
    "id": "290d89ec-f840-4729-8557-ecb27f8b7908",
    "creatorName": "lingq"
  },
  {
    "createdAt": "2025-12-02T03:38:30.418Z",
    "championName": "Nami",
    "username": "toanproquangau",
    "user_sub": "6498a4b8-a011-70a1-5f28-627c7ea26aa5",
    "id": "5c4ac148-4acf-459a-b89a-ff2fe390ce31",
    "creatorName": "Vô Danh"
  },
  {
    "createdAt": "2025-11-28T03:26:31.555Z",
    "championName": "Nami",
    "username": "evin123",
    "user_sub": "64b81448-0021-70b7-759a-080d73ea41fd",
    "id": "5c4ac148-4acf-459a-b89a-ff2fe390ce31",
    "creatorName": "Vô Danh"
  },
  {
    "createdAt": "2026-01-19T11:44:07.925Z",
    "championName": "Aurelion Sol",
    "username": "azm0deus1467",
    "user_sub": "a4b8a428-e0c1-70a9-3863-3bf9b3acff4f",
    "id": "a14dae93-91aa-4bb5-87df-0f682d164f57",
    "creatorName": "Vô Danh"
  },
  {
    "createdAt": "2025-12-02T03:38:27.611Z",
    "championName": "Warwick",
    "username": "toanproquangau",
    "user_sub": "6498a4b8-a011-70a1-5f28-627c7ea26aa5",
    "id": "80b0ebe9-d0e3-480f-9bc2-75c03bb3cfa9",
    "creatorName": "Vô Danh"
  },
  {
    "createdAt": "2026-01-19T11:43:52.306Z",
    "championName": "Bard",
    "username": "azm0deus1467",
    "user_sub": "a4b8a428-e0c1-70a9-3863-3bf9b3acff4f",
    "id": "9dc84553-667d-4b20-87cd-11d3a9d657c4",
    "creatorName": "Vô Danh"
  },
  {
    "createdAt": "2026-01-23T05:56:43.772Z",
    "championName": "Teemo Phong Linh Tiểu Quái",
    "username": "lizz",
    "user_sub": "14580488-a001-70df-4629-191850b75423",
    "id": "8fac2d99-e15d-4d0d-bf45-f387353597eb",
    "creatorName": "Vô Danh"
  },
  {
    "createdAt": "2026-03-23T09:09:55.698Z",
    "championName": "Jhin",
    "username": "thevirtuoso",
    "user_sub": "54c89418-5001-7064-a4db-714fcc6135dc",
    "id": "beccd681-786a-4b36-9012-36290966131a",
    "creatorName": "Vô Danh"
  },
  {
    "createdAt": "2026-02-27T03:10:20.387Z",
    "championName": "Jhin",
    "username": "lingq",
    "user_sub": "d4882408-b0d1-70bc-e3d3-13ef8cb11069",
    "id": "beccd681-786a-4b36-9012-36290966131a",
    "creatorName": "Vô Danh"
  },
  {
    "createdAt": "2026-03-23T09:09:43.455Z",
    "championName": "Jhin",
    "username": "thevirtuoso",
    "user_sub": "54c89418-5001-7064-a4db-714fcc6135dc",
    "id": "911e7c2d-9a6a-4b5e-ae22-2c0073fa45f2",
    "creatorName": "Vô Danh"
  },
  {
    "createdAt": "2026-01-04T06:47:19.692Z",
    "championName": "Norra",
    "username": "vuthinh2345",
    "user_sub": "14d8f4d8-a001-7085-e5d5-d2d63f2531ef",
    "id": "537fec40-92a6-4b26-b6ad-3d56bc489c5a",
    "creatorName": "Vô Danh"
  },
  {
    "createdAt": "2026-01-19T11:32:53.070Z",
    "championName": "Norra",
    "username": "azm0deus1467",
    "user_sub": "a4b8a428-e0c1-70a9-3863-3bf9b3acff4f",
    "id": "537fec40-92a6-4b26-b6ad-3d56bc489c5a",
    "creatorName": "Vô Danh"
  },
  {
    "createdAt": "2026-01-19T11:33:36.202Z",
    "championName": "Lux: rạng ngời",
    "username": "azm0deus1467",
    "user_sub": "a4b8a428-e0c1-70a9-3863-3bf9b3acff4f",
    "id": "90bf090c-cbc0-47d1-8923-784f5793c6fe",
    "creatorName": "Vô Danh"
  },
  {
    "createdAt": "2026-01-04T06:47:44.772Z",
    "championName": "Ekko",
    "username": "vuthinh2345",
    "user_sub": "14d8f4d8-a001-7085-e5d5-d2d63f2531ef",
    "id": "23a7d443-e478-4731-bd6e-55f47041a184",
    "creatorName": "Vô Danh"
  },
  {
    "createdAt": "2026-01-19T11:42:48.712Z",
    "championName": "Ekko",
    "username": "azm0deus1467",
    "user_sub": "a4b8a428-e0c1-70a9-3863-3bf9b3acff4f",
    "id": "23a7d443-e478-4731-bd6e-55f47041a184",
    "creatorName": "Vô Danh"
  },
  {
    "createdAt": "2025-12-02T03:38:26.099Z",
    "championName": "Thresh",
    "username": "toanproquangau",
    "user_sub": "6498a4b8-a011-70a1-5f28-627c7ea26aa5",
    "id": "1ccb21e2-0616-44c1-aaf8-c3b089980063",
    "creatorName": "Vô Danh"
  },
  {
    "createdAt": "2026-01-04T06:47:37.276Z",
    "championName": "Evelynn",
    "username": "vuthinh2345",
    "user_sub": "14d8f4d8-a001-7085-e5d5-d2d63f2531ef",
    "id": "0a81d6c8-af69-4a6e-aa33-d52301898742",
    "creatorName": "Vô Danh"
  },
  {
    "createdAt": "2025-12-02T03:38:22.679Z",
    "championName": "Nami",
    "username": "toanproquangau",
    "user_sub": "6498a4b8-a011-70a1-5f28-627c7ea26aa5",
    "id": "dde2e696-dd40-4c43-bbcd-417220cfc7a6",
    "creatorName": "Vô Danh"
  },
  {
    "createdAt": "2026-01-19T11:45:16.395Z",
    "championName": "Nami",
    "username": "azm0deus1467",
    "user_sub": "a4b8a428-e0c1-70a9-3863-3bf9b3acff4f",
    "id": "dde2e696-dd40-4c43-bbcd-417220cfc7a6",
    "creatorName": "Vô Danh"
  },
  {
    "createdAt": "2026-02-27T06:04:55.245Z",
    "championName": "Rồng Ngàn Tuổi",
    "username": "lingq",
    "user_sub": "d4882408-b0d1-70bc-e3d3-13ef8cb11069",
    "id": "bda7c2dd-1ab3-439d-a045-10974857ad7d",
    "creatorName": "Vô Danh"
  }
]